search_tools/__init__.py
search_tools/character_search.py
poseidon_bay-0.1.dist-info/LICENCE.txt
poseidon_bay-0.1.dist-info/METADATA
poseidon_bay-0.1.dist-info/WHEEL
poseidon_bay-0.1.dist-info/top_level.txt
poseidon_bay-0.1.dist-info/RECORD
