Metadata-Version: 2.1
Name: poseidon_bay
Version: 0.1
Summary: Contains Poseidon Bay search tools
Home-page: https://github.com/PyChala/Search-Tools
Author: Chrispine Mwape
Author-email: jrchrismwape@gmail.com
Classifier: Programming Language :: Python :: 3
Classifier: License :: OSI Approved :: MIT License
Classifier: Operating System :: OS Independent
Requires-Python: >=3.6
License-File: LICENCE.txt
